wagtail_localize_rws_languagecloud/__init__.py
wagtail_localize_rws_languagecloud/apps.py
wagtail_localize_rws_languagecloud/checks.py
wagtail_localize_rws_languagecloud/emails.py
wagtail_localize_rws_languagecloud/forms.py
wagtail_localize_rws_languagecloud/importer.py
wagtail_localize_rws_languagecloud/models.py
wagtail_localize_rws_languagecloud/rws_client.py
wagtail_localize_rws_languagecloud/signals.py
wagtail_localize_rws_languagecloud/sync.py
wagtail_localize_rws_languagecloud/views.py
wagtail_localize_rws_languagecloud/wagtail_hooks.py
wagtail_localize_rws_languagecloud/management/__init__.py
wagtail_localize_rws_languagecloud/management/commands/__init__.py
wagtail_localize_rws_languagecloud/management/commands/create_missing_rws_project_settings.py
wagtail_localize_rws_languagecloud/management/commands/sync_rws.py
wagtail_localize_rws_languagecloud/management/commands/update_translated_pages.py
wagtail_localize_rws_languagecloud/migrations/0001_initial.py
wagtail_localize_rws_languagecloud/migrations/0002_auto_20210914_1406.py
wagtail_localize_rws_languagecloud/migrations/0003_auto_20211008_1132.py
wagtail_localize_rws_languagecloud/migrations/0004_add_status_change_order.py
wagtail_localize_rws_languagecloud/migrations/0005_languagecloudprojectsettings.py
wagtail_localize_rws_languagecloud/migrations/0006_languagecloudfile_revision.py
wagtail_localize_rws_languagecloud/migrations/__init__.py
wagtail_localize_rws_languagecloud/static/wagtail_localize_rws_languagecloud/css/wagtail-localize-overrides.css
wagtail_localize_rws_languagecloud/static/wagtail_localize_rws_languagecloud/js/.gitignore
wagtail_localize_rws_languagecloud/static_src/custom.d.ts
wagtail_localize_rws_languagecloud/static_src/main.tsx
wagtail_localize_rws_languagecloud/templates/wagtail_localize/admin/edit_translation.html
wagtail_localize_rws_languagecloud/templates/wagtail_localize_rws_languagecloud/admin/languagecloud_report.html
wagtail_localize_rws_languagecloud-0.8.1.dist-info/LICENSE
wagtail_localize_rws_languagecloud-0.8.1.dist-info/METADATA
wagtail_localize_rws_languagecloud-0.8.1.dist-info/WHEEL
wagtail_localize_rws_languagecloud-0.8.1.dist-info/top_level.txt
wagtail_localize_rws_languagecloud-0.8.1.dist-info/RECORD
