Metadata-Version: 2.1
Name: wagtail-localize-rws-languagecloud
Version: 0.8.1
Summary: Translate and localize Wagtail CMS content with RWS LanguageCloud
Home-page: UNKNOWN
Author: Chris Shaw
Author-email: chris.shaw@torchbox.com
License: BSD
Platform: UNKNOWN
Classifier: Development Status :: 3 - Alpha
Classifier: Intended Audience :: Developers
Classifier: License :: OSI Approved :: BSD License
Classifier: Operating System :: OS Independent
Classifier: Programming Language :: Python
Classifier: Programming Language :: Python :: 3
Classifier: Programming Language :: Python :: 3.7
Classifier: Programming Language :: Python :: 3.8
Classifier: Programming Language :: Python :: 3.9
Classifier: Framework :: Django
Classifier: Framework :: Django :: 2.2
Classifier: Framework :: Django :: 3.1
Classifier: Framework :: Django :: 3.2
Classifier: Framework :: Wagtail
Classifier: Framework :: Wagtail :: 2
License-File: LICENSE
Requires-Dist: Django (<3.3,>=3.0)
Requires-Dist: Wagtail (<2.16,>=2.12)
Requires-Dist: wagtail-localize (>=1.0.1)
Provides-Extra: testing
Requires-Dist: dj-database-url (==0.5.0) ; extra == 'testing'
Requires-Dist: freezegun (==0.3.15) ; extra == 'testing'
Requires-Dist: responses (==0.13.4) ; extra == 'testing'
Requires-Dist: flake8 (==3.9.2) ; extra == 'testing'
Requires-Dist: black (==22.3.0) ; extra == 'testing'
Requires-Dist: isort (==5.9.3) ; extra == 'testing'
